odoo/addons/product_variant_company/README.rst
odoo/addons/product_variant_company/__init__.py
odoo/addons/product_variant_company/__manifest__.py
odoo/addons/product_variant_company/i18n/es.po
odoo/addons/product_variant_company/i18n/it.po
odoo/addons/product_variant_company/i18n/product_variant_company.pot
odoo/addons/product_variant_company/models/__init__.py
odoo/addons/product_variant_company/models/product_product.py
odoo/addons/product_variant_company/readme/CONTRIBUTORS.rst
odoo/addons/product_variant_company/readme/DESCRIPTION.rst
odoo/addons/product_variant_company/security/product_security.xml
odoo/addons/product_variant_company/static/description/icon.png
odoo/addons/product_variant_company/static/description/index.html
odoo/addons/product_variant_company/tests/__init__.py
odoo/addons/product_variant_company/tests/test_product_variant_company.py
odoo14_addon_product_variant_company-14.0.1.0.1.dev6.dist-info/METADATA
odoo14_addon_product_variant_company-14.0.1.0.1.dev6.dist-info/WHEEL
odoo14_addon_product_variant_company-14.0.1.0.1.dev6.dist-info/top_level.txt
odoo14_addon_product_variant_company-14.0.1.0.1.dev6.dist-info/RECORD
